{"name":"MWO LCO HK Project (HD 10700)","proposal":PROPOSAL_ID,"ipp_value":1.05,"operator":"SINGLE","observation_type":"NORMAL","requests":[{"acceptability_threshold":90,"configurations":[{"type":"NRES_SPECTRUM","instrument_type":"1M0-NRES-SCICAM","instrument_configs":[{"bin_x":1,"bin_y":1,"exposure_count":"2","exposure_time":"143","mode":"default","rotator_mode":"","extra_params":{},"optical_elements":{}}],"acquisition_config":{"mode":"BRIGHTEST","extra_params":{}},"guiding_config":{"mode":"ON","extra_params":{}},"target":{"name":"HD 10700","type":"ICRS","ra":26.0170142608,"dec":-15.9374795978,"proper_motion_ra":-1721.05,"proper_motion_dec":854.16,"epoch":2000,"parallax":273.96},"constraints":{"max_airmass":"2.0","min_lunar_distance":"0"}}],"windows":windows,"location":{"telescope_class":"1m0"}}]}