{"proposal":PROPOSAL_ID,"ipp_value":"1.1","operator":"SINGLE","observation_type":"NORMAL","requests":[{"windows":windows,"location":{"telescope_class":"1m0"},"configurations":[{"type":"NRES_SPECTRUM","instrument_type":"1M0-NRES-SCICAM","extra_params":{},"target":{"name":"HD 176051","type":"ICRS","ra":284.2567083,"dec":32.9012694,"proper_motion_ra":"201.96","proper_motion_dec":"-145.46","epoch":2000,"parallax":0},"constraints":{"max_airmass":"2.0","min_lunar_distance":"0"},"instrument_configs":[{"mode":"","exposure_time":"360","exposure_count":"2","rotator_mode":"VFLOAT","extra_params":{},"optical_elements":{},"bin_x":1,"bin_y":1}],"guiding_config":{"mode":"ON","extra_params":{}},"acquisition_config":{"mode":"BRIGHTEST","extra_params":{}}}]}],"name":"LCO HK project (HD 176051)"}
